allen_brain_colormaps/__init__.py
allen_brain_colormaps-0.1.2.dist-info/licenses/LICENSE
allen_brain_colormaps-0.1.2.dist-info/METADATA
allen_brain_colormaps-0.1.2.dist-info/WHEEL
allen_brain_colormaps-0.1.2.dist-info/entry_points.txt
allen_brain_colormaps-0.1.2.dist-info/top_level.txt
allen_brain_colormaps-0.1.2.dist-info/RECORD
