Metadata-Version: 2.4
Name: allen-brain-colormaps
Version: 0.1.2
Summary: Matplotlib and seaborn compatible colormaps for human brain cell types from the Allen Institute Brain Atlas
Author-email: Matthias Flotho <matthias.flotho@ccb.uni-saarland.de>
Maintainer-email: Matthias Flotho <matthias.flotho@ccb.uni-saarland.de>
License-Expression: MIT
Project-URL: Homepage, https://github.com/maflot/allen-brain-colormaps
Project-URL: Repository, https://github.com/maflot/allen-brain-colormaps
Project-URL: Documentation, https://allen-brain-colormaps.readthedocs.io/
Project-URL: Bug Tracker, https://github.com/maflot/allen-brain-colormaps/issues
Project-URL: Release Notes, https://github.com/maflot/allen-brain-colormaps/releases
Project-URL: Allen Institute, https://alleninstitute.org/
Project-URL: Brain Atlas, https://portal.brain-map.org/
Keywords: neuroscience,single-cell,visualization,colormap,matplotlib,seaborn,allen-brain-atlas,human-brain,cell-types,transcriptomics
Classifier: Development Status :: 4 - Beta
Classifier: Intended Audience :: Science/Research
Classifier: Topic :: Scientific/Engineering :: Bio-Informatics
Classifier: Topic :: Scientific/Engineering :: Visualization
Classifier: Topic :: Scientific/Engineering :: Medical Science Apps.
Classifier: Programming Language :: Python :: 3
Classifier: Programming Language :: Python :: 3.8
Classifier: Programming Language :: Python :: 3.9
Classifier: Programming Language :: Python :: 3.10
Classifier: Programming Language :: Python :: 3.11
Classifier: Programming Language :: Python :: 3.12
Classifier: Operating System :: OS Independent
Classifier: Natural Language :: English
Requires-Python: >=3.8
License-File: LICENSE
Requires-Dist: matplotlib>=3.5.0
Requires-Dist: seaborn>=0.11.0
Requires-Dist: numpy>=1.19.0
Provides-Extra: dev
Requires-Dist: pytest>=7.0; extra == "dev"
Requires-Dist: pytest-cov>=4.0; extra == "dev"
Requires-Dist: black>=22.0; extra == "dev"
Requires-Dist: flake8>=5.0; extra == "dev"
Requires-Dist: isort>=5.0; extra == "dev"
Requires-Dist: mypy>=1.0; extra == "dev"
Requires-Dist: pre-commit>=2.20; extra == "dev"
Provides-Extra: docs
Requires-Dist: sphinx>=5.0; extra == "docs"
Requires-Dist: sphinx-rtd-theme>=1.0; extra == "docs"
Requires-Dist: myst-parser>=0.18; extra == "docs"
Requires-Dist: sphinx-autodoc-typehints>=1.19; extra == "docs"
Provides-Extra: test
Requires-Dist: pytest>=7.0; extra == "test"
Requires-Dist: pytest-cov>=4.0; extra == "test"
Requires-Dist: pytest-xdist>=2.5; extra == "test"
Provides-Extra: all
Requires-Dist: allen-brain-colormaps[dev,docs,test]; extra == "all"
Dynamic: license-file
